[
    {
        "id": 1, 
        "name": "9am Monday Lesson",
        "price": 30,
        "category": null,
        "quantity": 1,
        "isInstrument": false,
        "isEquipment": false,
        "isLesson": true,
        "instructor": null,
        "student": null,
        "isFull": false,
        "startTime": "9am",
        "weekDay": "Monday"
    },
    {
        "id": 2, 
        "name": "9:30am Monday Lesson",
        "price": 30,
        "category": null,
        "quantity": 1,
        "isInstrument": false,
        "isEquipment": false,
        "isLesson": true,
        "instructor": null,
        "student": null,
        "isFull": false,
        "startTime": "9:30am",
        "weekDay": "Monday"
    },
    {
        "id": 3, 
        "name": "10am Monday Lesson",
        "price": 30,
        "category": null,
        "quantity": 1,
        "isInstrument": false,
        "isEquipment": false,
        "isLesson": true,
        "instructor": null,
        "student": null,
        "isFull": false,
        "startTime": "10am",
        "weekDay": "Monday"
    },
    {
        "id": 4, 
        "name": "10:30am Monday Lesson",
        "price": 30,
        "category": null,
        "quantity": 1,
        "isInstrument": false,
        "isEquipment": false,
        "isLesson": true,
        "instructor": null,
        "student": null,
        "isFull": false,
        "startTime": "10:30am",
        "weekDay": "Monday"
    },
    {
        "id": 5, 
        "name": "11am Monday Lesson",
        "price": 30,
        "category": null,
        "quantity": 1,
        "isInstrument": false,
        "isEquipment": false,
        "isLesson": true,
        "instructor": null,
        "student": null,
        "isFull": false,
        "startTime": "11am",
        "weekDay": "Monday"
    },
    {
        "id": 6, 
        "name": "11:30am Monday Lesson",
        "price": 30,
        "category": null,
        "quantity": 1,
        "isInstrument": false,
        "isEquipment": false,
        "isLesson": true,
        "instructor": null,
        "student": null,
        "isFull": false,
        "startTime": "11:30am",
        "weekDay": "Monday"
    },
    {
        "id": 7, 
        "name": "12pm Monday Lesson",
        "price": 30,
        "category": null,
        "quantity": 1,
        "isInstrument": false,
        "isEquipment": false,
        "isLesson": true,
        "instructor": null,
        "student": null,
        "isFull": false,
        "startTime": "12pm",
        "weekDay": "Monday"
    },
    {
        "id": 8, 
        "name": "12:30pm Monday Lesson",
        "price": 30,
        "category": null,
        "quantity": 1,
        "isInstrument": false,
        "isEquipment": false,
        "isLesson": true,
        "instructor": null,
        "student": null,
        "isFull": false,
        "startTime": "12:30pm",
        "weekDay": "Monday"
    },
    {
        "id": 9, 
        "name": "1pm Monday Lesson",
        "price": 30,
        "category": null,
        "quantity": 1,
        "isInstrument": false,
        "isEquipment": false,
        "isLesson": true,
        "instructor": null,
        "student": null,
        "isFull": false,
        "startTime": "1pm",
        "weekDay": "Monday"
    },
    {
        "id": 10, 
        "name": "1:30pm Monday Lesson",
        "price": 30,
        "category": null,
        "quantity": 1,
        "isInstrument": false,
        "isEquipment": false,
        "isLesson": true,
        "instructor": null,
        "student": null,
        "isFull": false,
        "startTime": "1:30pm",
        "weekDay": "Monday"
    },
    {
        "id": 11, 
        "name": "2pm Monday Lesson",
        "price": 30,
        "category": null,
        "quantity": 1,
        "isInstrument": false,
        "isEquipment": false,
        "isLesson": true,
        "instructor": null,
        "student": null,
        "isFull": false,
        "startTime": "2pm",
        "weekDay": "Monday"
    },
    {
        "id": 12, 
        "name": "2:30pm Monday Lesson",
        "price": 30,
        "category": null,
        "quantity": 1,
        "isInstrument": false,
        "isEquipment": false,
        "isLesson": true,
        "instructor": null,
        "student": null,
        "isFull": false,
        "startTime": "2:30pm",
        "weekDay": "Monday"
    },
    {
        "id": 13, 
        "name": "3pm Monday Lesson",
        "price": 30,
        "category": null,
        "quantity": 1,
        "isInstrument": false,
        "isEquipment": false,
        "isLesson": true,
        "instructor": null,
        "student": null,
        "isFull": false,
        "startTime": "3pm",
        "weekDay": "Monday"
    },
    {
        "id": 14, 
        "name": "3:30pm Monday Lesson",
        "price": 30,
        "category": null,
        "quantity": 1,
        "isInstrument": false,
        "isEquipment": false,
        "isLesson": true,
        "instructor": null,
        "student": null,
        "isFull": false,
        "startTime": "3:30pm",
        "weekDay": "Monday"
    },
    {
        "id": 15, 
        "name": "4pm Monday Lesson",
        "price": 30,
        "category": null,
        "quantity": 1,
        "isInstrument": false,
        "isEquipment": false,
        "isLesson": true,
        "instructor": null,
        "student": null,
        "isFull": false,
        "startTime": "4pm",
        "weekDay": "Monday"
    },
    {
        "id": 16, 
        "name": "4:30pm Monday Lesson",
        "price": 30,
        "category": null,
        "quantity": 1,
        "isInstrument": false,
        "isEquipment": false,
        "isLesson": true,
        "instructor": null,
        "student": null,
        "isFull": false,
        "startTime": "4:30pm",
        "weekDay": "Monday"
    },
    {
        "id": 17, 
        "name": "9am Tuesday Lesson",
        "price": 30,
        "category": null,
        "quantity": 1,
        "isInstrument": false,
        "isEquipment": false,
        "isLesson": true,
        "instructor": null,
        "student": null,
        "isFull": false,
        "startTime": "9am",
        "weekDay": "Tuesday"
    },
    {
        "id": 18, 
        "name": "9:30am Tuesday Lesson",
        "price": 30,
        "category": null,
        "quantity": 1,
        "isInstrument": false,
        "isEquipment": false,
        "isLesson": true,
        "instructor": null,
        "student": null,
        "isFull": false,
        "startTime": "9:30am",
        "weekDay": "Tuesday"
    },
    {
        "id": 19, 
        "name": "10am Tuesday Lesson",
        "price": 30,
        "category": null,
        "quantity": 1,
        "isInstrument": false,
        "isEquipment": false,
        "isLesson": true,
        "instructor": null,
        "student": null,
        "isFull": false,
        "startTime": "10am",
        "weekDay": "Tuesday"
    },
    {
        "id": 20, 
        "name": "10:30am Tuesday Lesson",
        "price": 30,
        "category": null,
        "quantity": 1,
        "isInstrument": false,
        "isEquipment": false,
        "isLesson": true,
        "instructor": null,
        "student": null,
        "isFull": false,
        "startTime": "10:30am",
        "weekDay": "Tuesday"
    },
    {
        "id": 21, 
        "name": "11am Tuesday Lesson",
        "price": 30,
        "category": null,
        "quantity": 1,
        "isInstrument": false,
        "isEquipment": false,
        "isLesson": true,
        "instructor": null,
        "student": null,
        "isFull": false,
        "startTime": "11am",
        "weekDay": "Tuesday"
    },
    {
        "id": 22, 
        "name": "11:30am Tuesday Lesson",
        "price": 30,
        "category": null,
        "quantity": 1,
        "isInstrument": false,
        "isEquipment": false,
        "isLesson": true,
        "instructor": null,
        "student": null,
        "isFull": false,
        "startTime": "11:30am",
        "weekDay": "Tuesday"
    },
    {
        "id": 23, 
        "name": "12pm Tuesday Lesson",
        "price": 30,
        "category": null,
        "quantity": 1,
        "isInstrument": false,
        "isEquipment": false,
        "isLesson": true,
        "instructor": null,
        "student": null,
        "isFull": false,
        "startTime": "12pm",
        "weekDay": "Tuesday"
    },
    {
        "id": 24, 
        "name": "12:30pm Tuesday Lesson",
        "price": 30,
        "category": null,
        "quantity": 1,
        "isInstrument": false,
        "isEquipment": false,
        "isLesson": true,
        "instructor": null,
        "student": null,
        "isFull": false,
        "startTime": "12:30pm",
        "weekDay": "Tuesday"
    },
    {
        "id": 25, 
        "name": "1pm Tuesday Lesson",
        "price": 30,
        "category": null,
        "quantity": 1,
        "isInstrument": false,
        "isEquipment": false,
        "isLesson": true,
        "instructor": null,
        "student": null,
        "isFull": false,
        "startTime": "1pm",
        "weekDay": "Tuesday"
    },
    {
        "id": 26, 
        "name": "1:30pm Tuesday Lesson",
        "price": 30,
        "category": null,
        "quantity": 1,
        "isInstrument": false,
        "isEquipment": false,
        "isLesson": true,
        "instructor": null,
        "student": null,
        "isFull": false,
        "startTime": "1:30pm",
        "weekDay": "Tuesday"
    },
    {
        "id": 27, 
        "name": "2pm Tuesday Lesson",
        "price": 30,
        "category": null,
        "quantity": 1,
        "isInstrument": false,
        "isEquipment": false,
        "isLesson": true,
        "instructor": null,
        "student": null,
        "isFull": false,
        "startTime": "2pm",
        "weekDay": "Tuesday"
    },
    {
        "id": 28, 
        "name": "2:30pm Tuesday Lesson",
        "price": 30,
        "category": null,
        "quantity": 1,
        "isInstrument": false,
        "isEquipment": false,
        "isLesson": true,
        "instructor": null,
        "student": null,
        "isFull": false,
        "startTime": "2:30pm",
        "weekDay": "Tuesday"
    },
    {
        "id": 29, 
        "name": "3pm Tuesday Lesson",
        "price": 30,
        "category": null,
        "quantity": 1,
        "isInstrument": false,
        "isEquipment": false,
        "isLesson": true,
        "instructor": null,
        "student": null,
        "isFull": false,
        "startTime": "3pm",
        "weekDay": "Tuesday"
    },
    {
        "id": 30, 
        "name": "3:30pm Tuesday Lesson",
        "price": 30,
        "category": null,
        "quantity": 1,
        "isInstrument": false,
        "isEquipment": false,
        "isLesson": true,
        "instructor": null,
        "student": null,
        "isFull": false,
        "startTime": "3:30pm",
        "weekDay": "Tuesday"
    },
    {
        "id": 31, 
        "name": "4pm Tuesday Lesson",
        "price": 30,
        "category": null,
        "quantity": 1,
        "isInstrument": false,
        "isEquipment": false,
        "isLesson": true,
        "instructor": null,
        "student": null,
        "isFull": false,
        "startTime": "4pm",
        "weekDay": "Tuesday"
    },
    {
        "id": 32, 
        "name": "4:30pm Tuesday Lesson",
        "price": 30,
        "category": null,
        "quantity": 1,
        "isInstrument": false,
        "isEquipment": false,
        "isLesson": true,
        "instructor": null,
        "student": null,
        "isFull": false,
        "startTime": "4:30pm",
        "weekDay": "Tuesday"
    },
    {
        "id": 33, 
        "name": "9am Wednesday Lesson",
        "price": 30,
        "category": null,
        "quantity": 1,
        "isInstrument": false,
        "isEquipment": false,
        "isLesson": true,
        "instructor": null,
        "student": null,
        "isFull": false,
        "startTime": "9am",
        "weekDay": "Wednesday"
    },
    {
        "id": 34, 
        "name": "9:30am Wednesday Lesson",
        "price": 30,
        "category": null,
        "quantity": 1,
        "isInstrument": false,
        "isEquipment": false,
        "isLesson": true,
        "instructor": null,
        "student": null,
        "isFull": false,
        "startTime": "9:30am",
        "weekDay": "Wednesday"
    },
    {
        "id": 35, 
        "name": "10am Wednesday Lesson",
        "price": 30,
        "category": null,
        "quantity": 1,
        "isInstrument": false,
        "isEquipment": false,
        "isLesson": true,
        "instructor": null,
        "student": null,
        "isFull": false,
        "startTime": "10am",
        "weekDay": "Wednesday"
    },
    {
        "id": 36, 
        "name": "10:30am Wednesday Lesson",
        "price": 30,
        "category": null,
        "quantity": 1,
        "isInstrument": false,
        "isEquipment": false,
        "isLesson": true,
        "instructor": null,
        "student": null,
        "isFull": false,
        "startTime": "10:30am",
        "weekDay": "Wednesday"
    },
    {
        "id": 37, 
        "name": "11am Wednesday Lesson",
        "price": 30,
        "category": null,
        "quantity": 1,
        "isInstrument": false,
        "isEquipment": false,
        "isLesson": true,
        "instructor": null,
        "student": null,
        "isFull": false,
        "startTime": "11am",
        "weekDay": "Wednesday"
    },
    {
        "id": 38, 
        "name": "11:30am Wednesday Lesson",
        "price": 30,
        "category": null,
        "quantity": 1,
        "isInstrument": false,
        "isEquipment": false,
        "isLesson": true,
        "instructor": null,
        "student": null,
        "isFull": false,
        "startTime": "11:30am",
        "weekDay": "Wednesday"
    },
    {
        "id": 39, 
        "name": "12pm Wednesday Lesson",
        "price": 30,
        "category": null,
        "quantity": 1,
        "isInstrument": false,
        "isEquipment": false,
        "isLesson": true,
        "instructor": null,
        "student": null,
        "isFull": false,
        "startTime": "12pm",
        "weekDay": "Wednesday"
    },
    {
        "id": 40, 
        "name": "12:30pm Wednesday Lesson",
        "price": 30,
        "category": null,
        "quantity": 1,
        "isInstrument": false,
        "isEquipment": false,
        "isLesson": true,
        "instructor": null,
        "student": null,
        "isFull": false,
        "startTime": "12:30pm",
        "weekDay": "Wednesday"
    },
    {
        "id": 41, 
        "name": "1pm Wednesday Lesson",
        "price": 30,
        "category": null,
        "quantity": 1,
        "isInstrument": false,
        "isEquipment": false,
        "isLesson": true,
        "instructor": null,
        "student": null,
        "isFull": false,
        "startTime": "1pm",
        "weekDay": "Wednesday"
    },
    {
        "id": 42, 
        "name": "1:30pm Wednesday Lesson",
        "price": 30,
        "category": null,
        "quantity": 1,
        "isInstrument": false,
        "isEquipment": false,
        "isLesson": true,
        "instructor": null,
        "student": null,
        "isFull": false,
        "startTime": "1:30pm",
        "weekDay": "Wednesday"
    },
    {
        "id": 43, 
        "name": "2pm Wednesday Lesson",
        "price": 30,
        "category": null,
        "quantity": 1,
        "isInstrument": false,
        "isEquipment": false,
        "isLesson": true,
        "instructor": null,
        "student": null,
        "isFull": false,
        "startTime": "2pm",
        "weekDay": "Wednesday"
    },
    {
        "id": 44, 
        "name": "2:30pm Wednesday Lesson",
        "price": 30,
        "category": null,
        "quantity": 1,
        "isInstrument": false,
        "isEquipment": false,
        "isLesson": true,
        "instructor": null,
        "student": null,
        "isFull": false,
        "startTime": "2:30pm",
        "weekDay": "Wednesday"
    },
    {
        "id": 45, 
        "name": "3pm Wednesday Lesson",
        "price": 30,
        "category": null,
        "quantity": 1,
        "isInstrument": false,
        "isEquipment": false,
        "isLesson": true,
        "instructor": null,
        "student": null,
        "isFull": false,
        "startTime": "3pm",
        "weekDay": "Wednesday"
    },
    {
        "id": 46, 
        "name": "3:30pm Wednesday Lesson",
        "price": 30,
        "category": null,
        "quantity": 1,
        "isInstrument": false,
        "isEquipment": false,
        "isLesson": true,
        "instructor": null,
        "student": null,
        "isFull": false,
        "startTime": "3:30pm",
        "weekDay": "Wednesday"
    },
    {
        "id": 47, 
        "name": "4pm Wednesday Lesson",
        "price": 30,
        "category": null,
        "quantity": 1,
        "isInstrument": false,
        "isEquipment": false,
        "isLesson": true,
        "instructor": null,
        "student": null,
        "isFull": false,
        "startTime": "4pm",
        "weekDay": "Wednesday"
    },
    {
        "id": 48, 
        "name": "4:30pm Wednesday Lesson",
        "price": 30,
        "category": null,
        "quantity": 1,
        "isInstrument": false,
        "isEquipment": false,
        "isLesson": true,
        "instructor": null,
        "student": null,
        "isFull": false,
        "startTime": "4:30pm",
        "weekDay": "Wednesday"
    },
    {
        "id": 49, 
        "name": "9am Thursday Lesson",
        "price": 30,
        "category": null,
        "quantity": 1,
        "isInstrument": false,
        "isEquipment": false,
        "isLesson": true,
        "instructor": null,
        "student": null,
        "isFull": false,
        "startTime": "9am",
        "weekDay": "Thursday"
    },
    {
        "id": 50, 
        "name": "9:30am Thursday Lesson",
        "price": 30,
        "category": null,
        "quantity": 1,
        "isInstrument": false,
        "isEquipment": false,
        "isLesson": true,
        "instructor": null,
        "student": null,
        "isFull": false,
        "startTime": "9:30am",
        "weekDay": "Thursday"
    },
    {
        "id": 51, 
        "name": "10am Thursday Lesson",
        "price": 30,
        "category": null,
        "quantity": 1,
        "isInstrument": false,
        "isEquipment": false,
        "isLesson": true,
        "instructor": null,
        "student": null,
        "isFull": false,
        "startTime": "10am",
        "weekDay": "Thursday"
    },
    {
        "id": 52, 
        "name": "10:30am Thursday Lesson",
        "price": 30,
        "category": null,
        "quantity": 1,
        "isInstrument": false,
        "isEquipment": false,
        "isLesson": true,
        "instructor": null,
        "student": null,
        "isFull": false,
        "startTime": "10:30am",
        "weekDay": "Thursday"
    },
    {
        "id": 53, 
        "name": "11am Thursday Lesson",
        "price": 30,
        "category": null,
        "quantity": 1,
        "isInstrument": false,
        "isEquipment": false,
        "isLesson": true,
        "instructor": null,
        "student": null,
        "isFull": false,
        "startTime": "11am",
        "weekDay": "Thursday"
    },
    {
        "id": 54, 
        "name": "11:30am Thursday Lesson",
        "price": 30,
        "category": null,
        "quantity": 1,
        "isInstrument": false,
        "isEquipment": false,
        "isLesson": true,
        "instructor": null,
        "student": null,
        "isFull": false,
        "startTime": "11:30am",
        "weekDay": "Thursday"
    },
    {
        "id": 55, 
        "name": "12pm Thursday Lesson",
        "price": 30,
        "category": null,
        "quantity": 1,
        "isInstrument": false,
        "isEquipment": false,
        "isLesson": true,
        "instructor": null,
        "student": null,
        "isFull": false,
        "startTime": "12pm",
        "weekDay": "Thursday"
    },
    {
        "id": 56, 
        "name": "12:30pm Thursday Lesson",
        "price": 30,
        "category": null,
        "quantity": 1,
        "isInstrument": false,
        "isEquipment": false,
        "isLesson": true,
        "instructor": null,
        "student": null,
        "isFull": false,
        "startTime": "12:30pm",
        "weekDay": "Thursday"
    },
    {
        "id": 57, 
        "name": "1pm Thursday Lesson",
        "price": 30,
        "category": null,
        "quantity": 1,
        "isInstrument": false,
        "isEquipment": false,
        "isLesson": true,
        "instructor": null,
        "student": null,
        "isFull": false,
        "startTime": "1pm",
        "weekDay": "Thursday"
    },
    {
        "id": 58, 
        "name": "1:30pm Thursday Lesson",
        "price": 30,
        "category": null,
        "quantity": 1,
        "isInstrument": false,
        "isEquipment": false,
        "isLesson": true,
        "instructor": null,
        "student": null,
        "isFull": false,
        "startTime": "1:30pm",
        "weekDay": "Thursday"
    },
    {
        "id": 59, 
        "name": "2pm Thursday Lesson",
        "price": 30,
        "category": null,
        "quantity": 1,
        "isInstrument": false,
        "isEquipment": false,
        "isLesson": true,
        "instructor": null,
        "student": null,
        "isFull": false,
        "startTime": "2pm",
        "weekDay": "Thursday"
    },
    {
        "id": 60, 
        "name": "2:30pm Thursday Lesson",
        "price": 30,
        "category": null,
        "quantity": 1,
        "isInstrument": false,
        "isEquipment": false,
        "isLesson": true,
        "instructor": null,
        "student": null,
        "isFull": false,
        "startTime": "2:30pm",
        "weekDay": "Thursday"
    },
    {
        "id": 61, 
        "name": "3pm Thursday Lesson",
        "price": 30,
        "category": null,
        "quantity": 1,
        "isInstrument": false,
        "isEquipment": false,
        "isLesson": true,
        "instructor": null,
        "student": null,
        "isFull": false,
        "startTime": "3pm",
        "weekDay": "Thursday"
    },
    {
        "id": 62, 
        "name": "3:30pm Thursday Lesson",
        "price": 30,
        "category": null,
        "quantity": 1,
        "isInstrument": false,
        "isEquipment": false,
        "isLesson": true,
        "instructor": null,
        "student": null,
        "isFull": false,
        "startTime": "3:30pm",
        "weekDay": "Thursday"
    },
    {
        "id": 63, 
        "name": "4pm Thursday Lesson",
        "price": 30,
        "category": null,
        "quantity": 1,
        "isInstrument": false,
        "isEquipment": false,
        "isLesson": true,
        "instructor": null,
        "student": null,
        "isFull": false,
        "startTime": "4pm",
        "weekDay": "Thursday"
    },
    {
        "id": 64, 
        "name": "4:30pm Thursday Lesson",
        "price": 30,
        "category": null,
        "quantity": 1,
        "isInstrument": false,
        "isEquipment": false,
        "isLesson": true,
        "instructor": null,
        "student": null,
        "isFull": false,
        "startTime": "4:30pm",
        "weekDay": "Thursday"
    },
    {
        "id": 65, 
        "name": "9am Friday Lesson",
        "price": 30,
        "category": null,
        "quantity": 1,
        "isInstrument": false,
        "isEquipment": false,
        "isLesson": true,
        "instructor": null,
        "student": null,
        "isFull": false,
        "startTime": "9am",
        "weekDay": "Friday"
    },
    {
        "id": 66, 
        "name": "9:30am Friday Lesson",
        "price": 30,
        "category": null,
        "quantity": 1,
        "isInstrument": false,
        "isEquipment": false,
        "isLesson": true,
        "instructor": null,
        "student": null,
        "isFull": false,
        "startTime": "9:30am",
        "weekDay": "Friday"
    },
    {
        "id": 67, 
        "name": "10am Friday Lesson",
        "price": 30,
        "category": null,
        "quantity": 1,
        "isInstrument": false,
        "isEquipment": false,
        "isLesson": true,
        "instructor": null,
        "student": null,
        "isFull": false,
        "startTime": "10am",
        "weekDay": "Friday"
    },
    {
        "id": 68, 
        "name": "10:30am Friday Lesson",
        "price": 30,
        "category": null,
        "quantity": 1,
        "isInstrument": false,
        "isEquipment": false,
        "isLesson": true,
        "instructor": null,
        "student": null,
        "isFull": false,
        "startTime": "10:30am",
        "weekDay": "Friday"
    },
    {
        "id": 69, 
        "name": "11am Friday Lesson",
        "price": 30,
        "category": null,
        "quantity": 1,
        "isInstrument": false,
        "isEquipment": false,
        "isLesson": true,
        "instructor": null,
        "student": null,
        "isFull": false,
        "startTime": "11am",
        "weekDay": "Friday"
    },
    {
        "id": 70, 
        "name": "11:30am Friday Lesson",
        "price": 30,
        "category": null,
        "quantity": 1,
        "isInstrument": false,
        "isEquipment": false,
        "isLesson": true,
        "instructor": null,
        "student": null,
        "isFull": false,
        "startTime": "11:30am",
        "weekDay": "Friday"
    },
    {
        "id": 71, 
        "name": "12pm Friday Lesson",
        "price": 30,
        "category": null,
        "quantity": 1,
        "isInstrument": false,
        "isEquipment": false,
        "isLesson": true,
        "instructor": null,
        "student": null,
        "isFull": false,
        "startTime": "12pm",
        "weekDay": "Friday"
    },
    {
        "id": 72, 
        "name": "12:30pm Friday Lesson",
        "price": 30,
        "category": null,
        "quantity": 1,
        "isInstrument": false,
        "isEquipment": false,
        "isLesson": true,
        "instructor": null,
        "student": null,
        "isFull": false,
        "startTime": "12:30pm",
        "weekDay": "Friday"
    },
    {
        "id": 73, 
        "name": "1pm Friday Lesson",
        "price": 30,
        "category": null,
        "quantity": 1,
        "isInstrument": false,
        "isEquipment": false,
        "isLesson": true,
        "instructor": null,
        "student": null,
        "isFull": false,
        "startTime": "1pm",
        "weekDay": "Friday"
    },
    {
        "id": 74, 
        "name": "1:30pm Friday Lesson",
        "price": 30,
        "category": null,
        "quantity": 1,
        "isInstrument": false,
        "isEquipment": false,
        "isLesson": true,
        "instructor": null,
        "student": null,
        "isFull": false,
        "startTime": "1:30pm",
        "weekDay": "Friday"
    },
    {
        "id": 74, 
        "name": "2pm Friday Lesson",
        "price": 30,
        "category": null,
        "quantity": 1,
        "isInstrument": false,
        "isEquipment": false,
        "isLesson": true,
        "instructor": null,
        "student": null,
        "isFull": false,
        "startTime": "2pm",
        "weekDay": "Friday"
    },
    {
        "id": 76, 
        "name": "2:30pm Friday Lesson",
        "price": 30,
        "category": null,
        "quantity": 1,
        "isInstrument": false,
        "isEquipment": false,
        "isLesson": true,
        "instructor": null,
        "student": null,
        "isFull": false,
        "startTime": "2:30pm",
        "weekDay": "Friday"
    },
    {
        "id": 77, 
        "name": "3pm Friday Lesson",
        "price": 30,
        "category": null,
        "quantity": 1,
        "isInstrument": false,
        "isEquipment": false,
        "isLesson": true,
        "instructor": null,
        "student": null,
        "isFull": false,
        "startTime": "3pm",
        "weekDay": "Friday"
    },
    {
        "id": 78, 
        "name": "3:30pm Friday Lesson",
        "price": 30,
        "category": null,
        "quantity": 1,
        "isInstrument": false,
        "isEquipment": false,
        "isLesson": true,
        "instructor": null,
        "student": null,
        "isFull": false,
        "startTime": "3:30pm",
        "weekDay": "Friday"
    },
    {
        "id": 79, 
        "name": "4pm Friday Lesson",
        "price": 30,
        "category": null,
        "quantity": 1,
        "isInstrument": false,
        "isEquipment": false,
        "isLesson": true,
        "instructor": null,
        "student": null,
        "isFull": false,
        "startTime": "4pm",
        "weekDay": "Friday"
    },
    {
        "id": 80, 
        "name": "4:30pm Friday Lesson",
        "price": 30,
        "category": null,
        "quantity": 1,
        "isInstrument": false,
        "isEquipment": false,
        "isLesson": true,
        "instructor": null,
        "student": null,
        "isFull": false,
        "startTime": "4:30pm",
        "weekDay": "Friday"
    }
]